silk_python-0.2.8.dist-info/RECORD
silk_python-0.2.8.dist-info/WHEEL
silk_python-0.2.8.dist-info/top_level.txt
silk_python-0.2.8.dist-info/METADATA
pysilk/__init__.py
pysilk/backends/__init__.py
pysilk/backends/cffi/build.py
pysilk/backends/cffi/__init__.py
pysilk/backends/cffi/_silk.abi3.so
pysilk/backends/cython/_silk.c
pysilk/backends/cython/_silk.pyx
pysilk/backends/cython/__init__.py
pysilk/backends/cython/_silk.pyi
pysilk/backends/cython/silk.pxd
pysilk/backends/cython/_silk.abi3.so
